README.rst
setup.py
daovoice/__init__.py
daovoice/api_operations.py
daovoice/client.py
daovoice/conf.py
daovoice/models.py
daovoice/service/__init__.py
daovoice/service/admin.py
daovoice/service/base_service.py
daovoice/service/conversation.py
daovoice/service/event.py
daovoice/service/message.py
daovoice/service/subscription.py
daovoice/service/user.py
daovoice/utils/__init__.py
daovoice/utils/data_mapper.py
daovoice_sdk.egg-info/PKG-INFO
daovoice_sdk.egg-info/SOURCES.txt
daovoice_sdk.egg-info/dependency_links.txt
daovoice_sdk.egg-info/not-zip-safe
daovoice_sdk.egg-info/requires.txt
daovoice_sdk.egg-info/top_level.txt
test/__init__.py