Metadata-Version: 1.1
Name: daovoice-sdk
Version: 0.0.8
Summary: DaoVoice Open API Python Sdk
Home-page: https://github.com/yowenter/daovoice-py-sdk
Author: Wenter W
Author-email: wenter.wu@gmail.com
License: MIT License
Keywords: DaoVoice Customer Management Python
Platform: UNKNOWN
Classifier: Programming Language :: Python :: 2.7
